fnnls/__init__.py
fnnls/fnnls.py
test/__init__.py
test/generate_figure.py
test/nnls_comparison.py
test/test_fnnls.py
fnnls-1.0.0.dist-info/LICENSE
fnnls-1.0.0.dist-info/METADATA
fnnls-1.0.0.dist-info/WHEEL
fnnls-1.0.0.dist-info/top_level.txt
fnnls-1.0.0.dist-info/RECORD
